president_speech/__init__.py
president_speech/cli.py
president_speech/crawling_speech.py
president_speech/extract_speech_from_pdf.py
president_speech/db/__init__.py
president_speech/db/connection_manager.py
president_speech/db/init.db
president_speech/db/parquet_interpreter.py
president_speech/db/search.py
president_speech/db/parquet/president_speech_ko.parquet
president_speech/db/parquet_tmp/nouns.parquet
president_speech/db/parquet_tmp/nouns_count.parquet
president_speech/nlp/__init__.py
president_speech/nlp/helper.py
president_speech/webapp/home.py
president_speech/webapp/pages/1_about.py
president_speech/webapp/pages/2_search_by_president.py
president_speech/webapp/pages/3_search_by_title.py
president_speech/webapp/pages/4_search_by_speech.py
president_speech/webapp/pages/5_frequency.py
president_speech/webapp/pages/6_LLM.py
president_speech/webapp/pages/7_partisanQR.py
president_speech-0.9.1.dist-info/METADATA
president_speech-0.9.1.dist-info/WHEEL
president_speech-0.9.1.dist-info/entry_points.txt
president_speech-0.9.1.dist-info/top_level.txt
president_speech-0.9.1.dist-info/RECORD
