Metadata-Version: 2.1
Name: president-speech
Version: 0.9.1
Summary: helper pip package module for analyzing presidential speech records (including basic data)
Author-email: dmario24 <data.mario24@gmail.com>
License: MIT
Project-URL: Homepage, https://github.com/edu-data-mario/president-speech
Project-URL: Bug Tracker, https://github.com/edu-data-mario/president-speech/issues
Requires-Python: !=3.9.7,>=3.8
Requires-Dist: streamlit ==1.26.0
Requires-Dist: termplotlib >=0.3.9
Requires-Dist: tabulate >=0.9.0
Requires-Dist: fastparquet >=2023.8.0
Requires-Dist: pyarrow >=13.0.0
Requires-Dist: requests >=2.31.0
Requires-Dist: pandas >=2.0.3
Requires-Dist: streamlit-chat >=0.1.1
Requires-Dist: konlpy >=0.6.0
Requires-Dist: dask >=2023.5.0
Requires-Dist: segno >=1.5.2
Requires-Dist: qrcode-artistic >=2.1.0
